cryptofusepy/__init__.py
cryptofusepy/client.py
cryptofusepy-0.1.1.dist-info/METADATA
cryptofusepy-0.1.1.dist-info/WHEEL
cryptofusepy-0.1.1.dist-info/entry_points.txt
cryptofusepy-0.1.1.dist-info/top_level.txt
cryptofusepy-0.1.1.dist-info/RECORD
