Metadata-Version: 2.1
Name: cryptofusepy
Version: 0.1.1
Summary: Python library for interacting with the CryptoFuse API
Author: Silenttttttt
Author-email: cryptofuse.net@gmail.com
Project-URL: Source Code, https://github.com/Os-brod/CryptoFusepy
Keywords: cryptofuse cryptocurrency cryptoswap swap crypto
Requires-Dist: requests
